LICENSE
README.md
ahn_cli/__init__.py
ahn_cli/config.py
ahn_cli/kwargs.py
ahn_cli/main.py
ahn_cli/process.py
ahn_cli/validator.py
ahn_cli/fetcher/__init__.py
ahn_cli/fetcher/geotiles.py
ahn_cli/fetcher/municipality.py
ahn_cli/fetcher/request.py
ahn_cli/fetcher/data/ahn_grid.geojson
ahn_cli/fetcher/data/ahn_subunit.geojson
ahn_cli/fetcher/data/municipality.geojson
ahn_cli/fetcher/data/municipality_simple.geojson
ahn_cli/manipulator/__init__.py
ahn_cli/manipulator/geojson.py
ahn_cli/manipulator/preview.py
ahn_cli/manipulator/ptc_handler.py
ahn_cli/manipulator/rasterizer.py
ahn_cli/manipulator/transformer.py
ahn_cli-0.3.5.dist-info/METADATA
ahn_cli-0.3.5.dist-info/WHEEL
ahn_cli-0.3.5.dist-info/entry_points.txt
ahn_cli-0.3.5.dist-info/licenses/LICENSE
ahn_cli-0.3.5.dist-info/RECORD
