Metadata-Version: 2.4
Name: ahn_cli
Version: 0.3.5
Summary: AHN CLI for downloading Dutch elevation point cloud data
Author-email: HideBa <baba.papa1120.ba@gmail.com>
License: MIT
License-File: LICENSE
Requires-Python: <3.13,>=3.10
Requires-Dist: click>=8.2.0
Requires-Dist: geopandas>=1.1.0
Requires-Dist: laspy[lazrs]>=2.6.0
Requires-Dist: polyscope>=2.4.0
Requires-Dist: rasterio>=1.4.0
Requires-Dist: requests>=2.32.0
Requires-Dist: shapely>=2.1.0
Requires-Dist: tqdm>=4.67.0
Requires-Dist: typing-extensions>=4.14.1
